<?xml version="1.0" encoding="utf-8" ?>
<dwsync>
<file name="gallery_5_1.htm" server="web27.ukraine.com.ua" local="129475072955983204" remote="129475072800000000" />
<file name="gallery_5_2.htm" server="web27.ukraine.com.ua" local="129475072842136693" remote="129475072800000000" />
<file name="gallery_5_3.htm" server="web27.ukraine.com.ua" local="129475072590272287" remote="129475072200000000" />
<file name="gallery_5_4.htm" server="web27.ukraine.com.ua" local="129475072469585384" remote="129475072200000000" />
<file name="gallery_5_1.htm" server="steli.ftp.ukraine.com.ua" local="130033252952494722" remote="130033252800000000" />
<file name="gallery_5_2.htm" server="steli.ftp.ukraine.com.ua" local="130033252858399340" remote="130033252800000000" />
<file name="gallery_5_3.htm" server="steli.ftp.ukraine.com.ua" local="130033252768134177" remote="130033252200000000" />
<file name="gallery_5_4.htm" server="steli.ftp.ukraine.com.ua" local="130033252599614538" remote="130033252200000000" />
<file name="gallery_5_5.htm" server="steli.ftp.ukraine.com.ua" local="130033252500658878" remote="130033252200000000" />
</dwsync>